README.md
setup.py
jsoncensor/__init__.py
jsoncensor/jsoncensor.py
jsoncensor.egg-info/PKG-INFO
jsoncensor.egg-info/SOURCES.txt
jsoncensor.egg-info/dependency_links.txt
jsoncensor.egg-info/top_level.txt