Metadata-Version: 1.0
Name: jsoncensor
Version: 0.1.0
Summary: Check json data in your python web service.
Home-page: https://github.com/Humbertzhang/jsoncensor
Author: HumbertZhang
Author-email: zhangke980623@icloud.com
License: UNKNOWN
Platform: UNKNOWN
